odoo8_addon_l10n_et_title-8.0.0.1.0.99.dev1-py2.7-nspkg.pth
odoo_addons/l10n_et_title/__openerp__.py
odoo_addons/l10n_et_title/__init__.py
odoo_addons/l10n_et_title/data/res.partner.title.csv
odoo_addons/l10n_et_title/static/description/icon.png
odoo8_addon_l10n_et_title-8.0.0.1.0.99.dev1.dist-info/top_level.txt
odoo8_addon_l10n_et_title-8.0.0.1.0.99.dev1.dist-info/WHEEL
odoo8_addon_l10n_et_title-8.0.0.1.0.99.dev1.dist-info/RECORD
odoo8_addon_l10n_et_title-8.0.0.1.0.99.dev1.dist-info/metadata.json
odoo8_addon_l10n_et_title-8.0.0.1.0.99.dev1.dist-info/DESCRIPTION.rst
odoo8_addon_l10n_et_title-8.0.0.1.0.99.dev1.dist-info/METADATA
odoo8_addon_l10n_et_title-8.0.0.1.0.99.dev1.dist-info/namespace_packages.txt
