Metadata-Version: 2.0
Name: odoo8-addon-l10n-et-title
Version: 8.0.0.1.0.99.dev1
Summary: Commonly used titles in Ethiopia
Home-page: http://www.clearict.com
Author: UNKNOWN
Author-email: UNKNOWN
License: AGPL-3
Platform: UNKNOWN
Requires-Dist: odoo (<9.0a,>=8.0a)
Requires-Dist: odoo8-addon-l10n-base
Classifier: Programming Language :: Python :: 2.7
Classifier: Framework :: Odoo
Classifier: License :: OSI Approved :: GNU Affero General Public License v3
